{
  "cart": [
    {
      "id": 3,
      "title": "Mens Cotton Jacket",
      "price": 55.99,
      "description": "great outerwear jackets for Spring/Autumn/Winter, suitable for many occasions, such as working, hiking, camping, mountain/rock climbing, cycling, traveling or other outdoors. Good gift choice for you or your family member. A warm hearted love to Father, husband or son in this thanksgiving or Christmas Day.",
      "category": "men's clothing",
      "qty": 1
    },
    {
      "id": 12,
      "title": "WD 4TB Gaming Drive Works with Playstation 4 Portable External Hard Drive",
      "price": 114,
      "description": "Expand your PS4 gaming experience, Play anywhere Fast and easy, setup Sleek design with high capacity, 3-year manufacturer's limited warranty",
      "category": "electronics",
      "qty": 18
    }
  ]
}